omniai_sdk/__init__.py
omniai_sdk/ai.py
omniai_sdk/analytics.py
omniai_sdk/campaigns.py
omniai_sdk/client.py
omniai_sdk/contacts.py
omniai_sdk/exceptions.py
omniai_sdk/messages.py
omniai_sdk-1.0.1.dist-info/METADATA
omniai_sdk-1.0.1.dist-info/WHEEL
omniai_sdk-1.0.1.dist-info/top_level.txt
omniai_sdk-1.0.1.dist-info/RECORD
