Metadata-Version: 2.4
Name: omniai-sdk
Version: 1.0.1
Summary: Official Python SDK for OmniAI API
Home-page: https://github.com/omniaiassist/omniai-python-sdk
Author: OmniAI Team
Author-email: dev@omniaiassist.com
Project-URL: Documentation, https://omniai.belizatech.com.br/support/documentation
Project-URL: Source, https://github.com/omniaiassist/omniai-python-sdk
Project-URL: Bug Reports, https://github.com/omniaiassist/omniai-python-sdk/issues
Keywords: omniai api sdk whatsapp messaging ai automation
Classifier: Development Status :: 5 - Production/Stable
Classifier: Intended Audience :: Developers
Classifier: Topic :: Software Development :: Libraries :: Python Modules
Classifier: License :: OSI Approved :: MIT License
Classifier: Programming Language :: Python :: 3
Classifier: Programming Language :: Python :: 3.7
Classifier: Programming Language :: Python :: 3.8
Classifier: Programming Language :: Python :: 3.9
Classifier: Programming Language :: Python :: 3.10
Classifier: Programming Language :: Python :: 3.11
Requires-Python: >=3.7
Requires-Dist: requests>=2.25.0
Provides-Extra: dev
Requires-Dist: pytest>=6.0; extra == "dev"
Requires-Dist: pytest-cov>=2.10; extra == "dev"
Requires-Dist: black>=21.0; extra == "dev"
Requires-Dist: flake8>=3.8; extra == "dev"
Dynamic: author
Dynamic: author-email
Dynamic: classifier
Dynamic: description
Dynamic: description-content-type
Dynamic: home-page
Dynamic: keywords
Dynamic: project-url
Dynamic: provides-extra
Dynamic: requires-dist
Dynamic: requires-python
Dynamic: summary
